MANIFEST.in
README.rst
setup.py
docs/HISTORY.txt
docs/LICENSE.GPL
docs/LICENSE.txt
ftw/__init__.py
ftw.testing.egg-info/PKG-INFO
ftw.testing.egg-info/SOURCES.txt
ftw.testing.egg-info/dependency_links.txt
ftw.testing.egg-info/entry_points.txt
ftw.testing.egg-info/namespace_packages.txt
ftw.testing.egg-info/not-zip-safe
ftw.testing.egg-info/requires.txt
ftw.testing.egg-info/top_level.txt
ftw/testing/__init__.py
ftw/testing/exceptions.py
ftw/testing/freezer.py
ftw/testing/genericsetup.py
ftw/testing/implementer.py
ftw/testing/integration_testing.py
ftw/testing/layer.py
ftw/testing/mailhost.py
ftw/testing/mailing.py
ftw/testing/patch.py
ftw/testing/quickinstaller.py
ftw/testing/staticuids.py
ftw/testing/testcase.py
ftw/testing/testing.py
ftw/testing/transaction_interceptor.py
ftw/testing/tests/__init__.py
ftw/testing/tests/configure.zcml
ftw/testing/tests/interfaces.py
ftw/testing/tests/test_component_registry_isolation_layer.py
ftw/testing/tests/test_console_script_layer.py
ftw/testing/tests/test_freezer.py
ftw/testing/tests/test_genericsetup.py
ftw/testing/tests/test_implementer.py
ftw/testing/tests/test_integration_testing.py
ftw/testing/tests/test_mailing.py
ftw/testing/tests/test_staticuids.py
ftw/testing/tests/test_temp_directory_layer.py
ftw/testing/tests/test_testcase.py
ftw/testing/tests/test_transaction_interceptor.py
ftw/testing/tests/views.py
ftw/testing/tests/views.zcml
ftw/testing/tests/Extensions/__init__.py
ftw/testing/tests/Extensions/install.py
ftw/testing/tests/profiles/dxtype.zcml
ftw/testing/tests/profiles/default/actions.xml
ftw/testing/tests/profiles/default/cssregistry.xml
ftw/testing/tests/profiles/dxtype/metadata.xml
ftw/testing/tests/profiles/dxtype/types.xml
ftw/testing/tests/profiles/dxtype/types/DXType.xml
ftw/testing/tests/profiles/uninstall/actions.xml
ftw/testing/tests/profiles/uninstall/cssregistry.xml
ftw/testing/tests/resources/paintitblack.css