Metadata-Version: 2.1
Name: ftw.testing
Version: 2.0.0
Summary: Provides some testing helpers and an advanced MockTestCase.
Home-page: https://github.com/4teamwork/ftw.testing
Author: 4teamwork AG
Author-email: mailto:info@4teamwork.ch
Maintainer: Jonas Baumann
License: GPL2
Keywords: ftw testing mocking testcase mock stub
Platform: UNKNOWN
Classifier: Framework :: Plone
Classifier: Framework :: Plone :: 4.3
Classifier: Framework :: Plone :: 5.1
Classifier: Framework :: Plone :: 5.2
Classifier: Programming Language :: Python
Classifier: Programming Language :: Python :: 2.7
Classifier: Programming Language :: Python :: 3.7
Classifier: Topic :: Software Development :: Libraries :: Python Modules
Provides-Extra: tests
